pysmtb/__init__.py
pysmtb/btf.py
pysmtb/geometry.py
pysmtb/image.py
pysmtb/iv.py
pysmtb/plotting.py
pysmtb/rendering.py
pysmtb/utils.py
pysmtb/tb/__init__.py
pysmtb/tb/tblogparser.py
pysmtb/tb/tbutils.py
pysmtb-0.2.11.dist-info/LICENSE
pysmtb-0.2.11.dist-info/METADATA
pysmtb-0.2.11.dist-info/WHEEL
pysmtb-0.2.11.dist-info/entry_points.txt
pysmtb-0.2.11.dist-info/top_level.txt
pysmtb-0.2.11.dist-info/RECORD
