Metadata-Version: 2.1
Name: pysmtb
Version: 0.2.11
Summary: python toolbox of (mostly) image-related helper / visualization functions
Home-page: https://github.com/smerzbach/pysmtb
Author: Sebastian Merzbach
Author-email: smerzbach@gmail.com
License: UNKNOWN
Platform: UNKNOWN
Classifier: Programming Language :: Python :: 3
Classifier: License :: OSI Approved :: MIT License
Classifier: Operating System :: OS Independent
Requires-Python: >=3.6
License-File: LICENSE
Requires-Dist: click
Requires-Dist: colour-science
Requires-Dist: imageio
Requires-Dist: matplotlib
Requires-Dist: numpy
Requires-Dist: tqdm
Provides-Extra: exr
Requires-Dist: openexr ; extra == 'exr'
Provides-Extra: iv
Requires-Dist: PyQt5 ; extra == 'iv'
Provides-Extra: plotting
Requires-Dist: PyQt5 ; extra == 'plotting'
Provides-Extra: rendering
Requires-Dist: PyQt5 ; extra == 'rendering'
Requires-Dist: pyembree ; extra == 'rendering'
Requires-Dist: trimesh ; extra == 'rendering'
Provides-Extra: tbutils
Requires-Dist: difflib ; extra == 'tbutils'
Requires-Dist: pandas ; extra == 'tbutils'
Requires-Dist: tensorboard ; extra == 'tbutils'
Requires-Dist: torch ; extra == 'tbutils'
